pyportify/__init__.py
pyportify/app.py
pyportify/copy_all.py
pyportify/google.py
pyportify/middlewares.py
pyportify/serializers.py
pyportify/server.py
pyportify/spotify.py
pyportify/spotify_appkey.key
pyportify/tests.py
pyportify/util.py
pyportify/gpsoauth/__init__.py
pyportify/gpsoauth/google.py
pyportify/gpsoauth/util.py
pyportify/pkcs1/__init__.py
pyportify/pkcs1/defaults.py
pyportify/pkcs1/exceptions.py
pyportify/pkcs1/keys.py
pyportify/pkcs1/mgf.py
pyportify/pkcs1/primes.py
pyportify/pkcs1/primitives.py
pyportify/pkcs1/rsaes_oaep.py
pyportify/static/index.html
pyportify/static/style.css
pyportify/static/css/animate.min.css
pyportify/static/css/app.css
pyportify/static/css/bootstrap-responsive.css
pyportify/static/css/bootstrap-responsive.min.css
pyportify/static/css/bootstrap.css
pyportify/static/css/bootstrap.min.css
pyportify/static/css/flat-ui.css
pyportify/static/css/font-awesome.min.css
pyportify/static/fonts/Flat-UI-Icons.dev.svg
pyportify/static/fonts/Flat-UI-Icons.eot
pyportify/static/fonts/Flat-UI-Icons.svg
pyportify/static/fonts/Flat-UI-Icons.ttf
pyportify/static/fonts/Flat-UI-Icons.woff
pyportify/static/fonts/FontAwesome.otf
pyportify/static/fonts/fontawesome-webfont.eot
pyportify/static/fonts/fontawesome-webfont.svg
pyportify/static/fonts/fontawesome-webfont.ttf
pyportify/static/fonts/fontawesome-webfont.woff
pyportify/static/fonts/icomoon-session.json
pyportify/static/icons/128.png
pyportify/static/icons/16.png
pyportify/static/icons/32.png
pyportify/static/icons/64.png
pyportify/static/img/angularjs.png
pyportify/static/img/appjs.png
pyportify/static/img/big_cover.png
pyportify/static/img/g.png
pyportify/static/img/glyphicons-halflings-white.png
pyportify/static/img/glyphicons-halflings.png
pyportify/static/img/no_album.png
pyportify/static/img/nodejs.png
pyportify/static/img/portify.svg
pyportify/static/img/s.png
pyportify/static/js/angular.js
pyportify/static/js/app.js
pyportify-0.4.1.dist-info/DESCRIPTION.rst
pyportify-0.4.1.dist-info/METADATA
pyportify-0.4.1.dist-info/RECORD
pyportify-0.4.1.dist-info/WHEEL
pyportify-0.4.1.dist-info/entry_points.txt
pyportify-0.4.1.dist-info/metadata.json
pyportify-0.4.1.dist-info/top_level.txt
