Metadata-Version: 2.0
Name: pyportify
Version: 0.4.1
Summary: App to transfer your spotify playlists to Google Play Music
Home-page: https://github.com/rckclmbr/pyportify
Author: Josh Braegger
Author-email: rckclmbr@gmail.com
License: Apache 2.0
Platform: UNKNOWN
Classifier: Environment :: Web Environment
Requires-Dist: aiohttp (==2.3.10)
Requires-Dist: requests (==2.18.4)
Requires-Dist: six (==1.11.0)
Requires-Dist: certifi (>=2017.11.5)
